pykovy/__init__.py
pykovy/chain.py
pykovy/errors.py
pykovy/utils.py
pykovy-1.1.dist-info/METADATA
pykovy-1.1.dist-info/RECORD
pykovy-1.1.dist-info/WHEEL
pykovy-1.1.dist-info/top_level.txt
